behaving/CONTRIBUTING.rst
behaving/__init__.py
behaving/environment.py
behaving/fsinspector.py
behaving/mail/__init__.py
behaving/mail/environment.py
behaving/mail/mock.py
behaving/mail/steps.py
behaving/notifications/__init__.py
behaving/notifications/gcm/__init__.py
behaving/notifications/gcm/environment.py
behaving/notifications/gcm/mock.py
behaving/notifications/gcm/steps.py
behaving/personas/__init__.py
behaving/personas/environment.py
behaving/personas/persona.py
behaving/personas/steps.py
behaving/sms/__init__.py
behaving/sms/environment.py
behaving/sms/mock.py
behaving/sms/steps.py
behaving/utils.py
behaving/web/__init__.py
behaving/web/environment.py
behaving/web/steps/__init__.py
behaving/web/steps/alerts.py
behaving/web/steps/basic.py
behaving/web/steps/browser.py
behaving/web/steps/css.py
behaving/web/steps/downloads.py
behaving/web/steps/forms.py
behaving/web/steps/frames.py
behaving/web/steps/links.py
behaving/web/steps/mouse.py
behaving/web/steps/tables.py
behaving/web/steps/url.py
behaving/web/steps/variables.py
behaving/web/steps/windows.py
behaving-3.2.1.dist-info/LICENSE.GPL
behaving-3.2.1.dist-info/LICENSE.txt
behaving-3.2.1.dist-info/METADATA
behaving-3.2.1.dist-info/WHEEL
behaving-3.2.1.dist-info/entry_points.txt
behaving-3.2.1.dist-info/RECORD
