Metadata-Version: 2.3
Name: behaving
Version: 3.2.1
Summary: BDD Behavior-Driven-Development testing
License: GPL
Keywords: BDD,Behavior-Driven-Development,testing
Author: Yiorgis Gozadinos
Author-email: ggozadinos@gmail.com
Maintainer: Yiorgis Gozadinos
Maintainer-email: ggozadinos@gmail.com
Requires-Python: >=3.9
Classifier: Development Status :: 5 - Production/Stable
Classifier: Intended Audience :: Developers
Classifier: License :: Other/Proprietary License
Classifier: Programming Language :: Python
Classifier: Programming Language :: Python :: 3
Classifier: Programming Language :: Python :: 3.9
Classifier: Programming Language :: Python :: 3.10
Classifier: Programming Language :: Python :: 3.11
Classifier: Programming Language :: Python :: 3.12
Classifier: Programming Language :: Python :: 3.13
Classifier: Topic :: Software Development :: Libraries
Classifier: Topic :: Software Development :: Libraries :: Python Modules
Classifier: Topic :: Software Development :: Quality Assurance
Classifier: Topic :: Software Development :: Testing
Requires-Dist: behave (>=1.2.6)
Requires-Dist: parse (>=1.20.2)
Requires-Dist: selenium (>=4)
Requires-Dist: splinter (>=0.21.0)
Project-URL: Repository, https://github.com/ggozad/behaving
